Metadata-Version: 1.1
Name: python-gyg
Version: 0.1
Summary: Python library for GetYourGuide API
Home-page: http://github.com//fukac99/python_gyg.git
Author: Lukas Toma
Author-email: toma.lukas@gmail.com
License: MIT
Keywords: getyourguide,travel,api,tours
Platform: UNKNOWN
Classifier: License :: OSI Approved :: MIT License
Classifier: Programming Language :: Python :: 2.7
